hvicorn/__init__.py
hvicorn/bot/__init__.py
hvicorn/bot/client.py
hvicorn/bot/optional_features.py
hvicorn/models/__init__.py
hvicorn/models/client/__init__.py
hvicorn/models/client/changecolor.py
hvicorn/models/client/changenick.py
hvicorn/models/client/chat.py
hvicorn/models/client/custom.py
hvicorn/models/client/emote.py
hvicorn/models/client/invite.py
hvicorn/models/client/join.py
hvicorn/models/client/ping.py
hvicorn/models/client/update_message.py
hvicorn/models/client/whisper.py
hvicorn/models/server/__init__.py
hvicorn/models/server/captcha.py
hvicorn/models/server/change_nick.py
hvicorn/models/server/chat.py
hvicorn/models/server/emote.py
hvicorn/models/server/info.py
hvicorn/models/server/invite.py
hvicorn/models/server/lockroom.py
hvicorn/models/server/online_add.py
hvicorn/models/server/online_remove.py
hvicorn/models/server/online_set.py
hvicorn/models/server/ratelimited.py
hvicorn/models/server/uncatched.py
hvicorn/models/server/update_message.py
hvicorn/models/server/update_user.py
hvicorn/models/server/warn.py
hvicorn/models/server/whisper.py
hvicorn/models/server/whisper_sent.py
hvicorn/utils/__init__.py
hvicorn/utils/generate_customid.py
hvicorn/utils/json_to_object.py
hvicorn/utils/optional_features.py
hvicorn-0.2.0.dist-info/licenses/LICENSE
hvicorn-0.2.0.dist-info/METADATA
hvicorn-0.2.0.dist-info/WHEEL
hvicorn-0.2.0.dist-info/top_level.txt
hvicorn-0.2.0.dist-info/RECORD
