Metadata-Version: 2.4
Name: hvicorn
Version: 0.2.0
Summary: A simple hack.chat bot framework with type hinting
Home-page: https://github.com/Hiyoteam/hvicorn
Author: 0x24a
Author-email: miku399993@gmail.com
Requires-Python: >=3.11
License-File: LICENSE
Requires-Dist: pydantic==2.7.3
Requires-Dist: setuptools==70.0.0
Requires-Dist: websocket-client==1.8.0
Requires-Dist: websockets==12.0
Dynamic: author
Dynamic: author-email
Dynamic: home-page
Dynamic: license-file
